bitbucket_batch.py
setup.py
bitbucket_batch.egg-info/PKG-INFO
bitbucket_batch.egg-info/SOURCES.txt
bitbucket_batch.egg-info/dependency_links.txt
bitbucket_batch.egg-info/entry_points.txt
bitbucket_batch.egg-info/top_level.txt