Metadata-Version: 1.0
Name: bitbucket-batch
Version: 0.1.2
Summary: A tool for bulk updating access to bitbucket.org repos.
Home-page: http://bitbucket.org/stephenmcd/bitbucket-batch/
Author: Stephen McDonald
Author-email: stephen.mc@gmail.com
License: BSD
Platform: UNKNOWN
Classifier: Development Status :: 4 - Beta
Classifier: Intended Audience :: Developers
Classifier: License :: OSI Approved :: BSD License
Classifier: Operating System :: POSIX
Classifier: Programming Language :: Python
